{
  "id": "1b1be06a-e3d7-4f96-be3b-021f1198e2ce",
  "title": "국가 흥망의 원인 - 부",
  "content": "「캘리포니아」공과대의 지구화학교수 「클레어·패터슨」박사는「로마」제국의 멸망이유는 은의 생산과 공급부족 때문이라고 말했다.대기오염을 연구하던 「패터슨」박사는 납의 공급사를 추구하던 끝에 고대의 은 생산을 조사하게 되었다.이 연구에서 그는 3세기께부터 줄어들기 시작한 「로마」의 은화공급으로 그 나라 경제의 뼈대가 허물어졌다는 결론에 도달했다. 원래 「로마」는 기원전50년에서 기원1백년에 이르는 기간 연간 3만ｔ에 달한 「이베리아」반도에서의 은 생산으로 교환경제를 번성시켰으나, 그후론 은의 매장량이 줄어 그 당시 기술로는 더 깊은 곳에 묻힌 은을 캐내지 못했고, 은화가 부족한 대신 물물교환경제로 후퇴, 결국은 경제파탄이 닥쳐왔다는 것이다.\n그래서 『어느 틈엔가 자기도 모르게 온몸의 피가 빠져 죽어버린 격』이 됐다고 한다. 「로마」제국의 막강한 군대도 은 생산을 위해 15만 명의 노예를 보급했어야 했다. 「패터슨」교수의 주장에 의하면「그리스」의 쇠망도 은 공급감소와 일치한다고 한다.그 당시 「라우리온」은광의 폐광과 더불어 「아테네」의 영화가 사라졌다는 것이며 중세암흑시대의 몰락도 마찬가지로, 근세의 흥기도 중부「유럽」에서의 대 은광 발견과 때를 같이 했다고 한다.",
  "color": "default",
  "labels": [
    "898f43eb-c79c-4781-9c09-9e88a458c8c7",
    "7614a8cc-7612-44a0-80ce-fcaffc04867d",
    "d681d9ed-1ad5-4666-a9d4-269e4225597d"
  ],
  "pinned": false,
  "archived": true,
  "inTrash": false,
  "reminder": null,
  "createdAt": "2022-01-19T10:42:24.890000",
  "updatedAt": "2022-01-19T11:55:23.970000"
}