{
  "id": "1dc5daf0-c374-4da7-b348-33315a77a939",
  "title": "battle it out",
  "content": "끝장을 볼 때까지 싸우다\n 경쟁을 벌이다, 치열하게 다투다, 승부를 겨루다\n\nThe two teams will battle it out in the finals.\n → 두 팀이 결승에서 치열하게 맞붙는다.\n\nFour startups are battling it out for market dominance.\n → 네 개 스타트업이 시장 지배력을 두고 각축을 벌이고 있다.\n\nAdolescence, The White Lotus, Severance and The Studio battle it out at the Emmy Awards \n〈Adolescence〉, 〈The White Lotus〉, 〈Severance〉, 〈The Studio〉가 에미상에서 맞붙는다",
  "color": "default",
  "labels": [
    "a5c06cbb-8579-44ca-9e9a-cd1c997f4b97"
  ],
  "pinned": false,
  "archived": true,
  "inTrash": false,
  "reminder": null,
  "createdAt": "2025-09-15T09:35:54.594000",
  "updatedAt": "2025-09-15T09:38:24.976000"
}