{
  "id": "2001d0ee-3542-4760-99f7-47b75202eb81",
  "title": "탁현(涿郡) =계(薊) = 연경(燕京) = (요)남경",
  "content": "![image](media/191cac2205d.bd627296eb0f9916.jpg)\n![image](media/191cf6d0e1d.85d20ca19b703bd4.jpg)\n![image](media/192e9807d80.861b1c651ff41052.jpg)\n![image](media/192e982f72b.85b31890811c3df8.jpg)\n![image](media/19431abedc0.bd4fbd04e347d1b1.jpg)\n![image](media/194f2c9bf81.a323cb84b07753e1.jpg)\n![image](media/194f2d126dd.b4f152ca3fcc88df.png)\n![image](media/19507055cb0.ac04d7c8d9e51dca.jpg)\n![image](media/1959d6c3697.8c896204122e1a42.jpg)\n\n\n\n치현(한국어: 기현, 중국어: 祁县, 병음: Qí Xiàn)은 중화인민공화국 산시성 진중시의 행정구역이다. \n소여고성은 기현고성이라고도 한다. 기현고성은 진상들의 중요 교역품인 차무역의 중심 문화구였다.\n\n북경반점\n기현 = 계현 = 탁군 = 범양 = 유주\n\n성헌식\n동군의 범현 역시 탁군의 탁현을 말하는 것이다. 탁군의 연혁에 의하면 위 문왕(조비) 7년(226년)에 탁군이 범양군으로 개명됐다가 서진의 무왕(사마염) 원년(265년)에 범양군을 범양국으로 개칭했다. 이후 북위 때인 386년 다시 범양군으로 바꿨다. 당나라 때인 618년 탁군을 파하고 유주로 개칭했고 624년 탁현을 범양현으로 바꾸었다가 안록산의 난 이후 범양군을 유주라 칭했다가 724년 유주를 범양군으로 바꿔 불렀다.\n현재 산동성의 서부와 접하는 (예전에 대야택(발해)과 접했던) 하남성의 동단 복양(濮陽)시 일대였던 동군에는 치우천왕의 무덤이 있는 산동성 수장현(현 유성시 양곡현)과 요임금의 무덤이 있는 산동성 하택시 견성현도 포함된다. 아마도 복양시 동북쪽에 있는 범현이 탁현이었을 가능성이 크다.\n관우는 유비, 장비와는 달리 하동군 해현(河東 解縣) 출신이다. <삼국지 촉서 관우열전>에 “관우(關羽)의 자는 운장(雲長) 본래 자는 장생(長生)이며 하동군 해현(河東解縣) 사람이다. 망명(亡命)해서 탁군(奔涿郡)으로 달아났다. 선주(先主=유비)가 고향에서 의병을 모으니 관우는 장비(張飛)와 함께 그를 위해 적을 막아냈다”고 기록돼 있다.\n당시 중국에는 한나라만이 존재했기 때문에 위 관우열전의 亡命奔涿郡(망명해서 탁군으로 달아났다)는 의미는 당시 유비와 장비는 탁군의 탁현에 살고 있던 한나라 사람이었으며 관우는 하동 해현에서 살았던 고구리 출신이었다는 것이다. 고구리에서 한나라로 망명한 관우가 얼마 후 탁군의 탁현을 지나게 됐는데 거기서 황건적을 토벌할 의병을 모집하려는 유비와 장비를 만났던 것이다. \n탁군이 지금의 북경시 서남부 탁주시라는 주장은 지명 이동된 것이다.\n\n위키\n탁주시의 옛 명칭은 탁녹, 탁읍, 탁군, 범양, 탁현이다. 탁주는 유비, 관우, 장비가 도원결의(桃園結義)를 했던 곳이다. \n\n지구인\n후한(後漢)의 광무제(光武帝)가 왕망(王莽), 왕랑(王郞) 등의 적대 세력들에 맞서 대결 상태에 있던 신(新)나라 말엽 및 그 이후 후한 초기의 역사를 기록한 사서들에 광무제의 이동 동선과 관련되어 '계(薊)' 또는 '계성(薊城)'이라는 지명이 자주 등장한다. 광무제 시기의 지명 '薊'는 한(漢)의 후국인 광양국(廣陽國)의 속현이자 치소였던 계현(薊縣)을 말하고, '薊城'은 계현에 있었던 광양국의 도성을 가리킨다.\n<『舊唐書』 지리지 幽州大都督府 薊縣>\n계현(薊縣) : 유주대도독부를 다스리는 곳이다. 옛날 연국(燕國)의 도읍이었다. 한(漢)에서는 계현(薊縣)이었고 광양국(廣陽國)에 속하였다.  \n薊 州所治 古之燕國都 漢為薊縣 屬廣陽國 \n《舊唐書(구당서)》 지리지 및 《隋書(수서)》 지리지의 기록들에 의하면 당(唐)의 幽州(대도독부)는 본래 수 양제(隋 煬帝) 재위 초기에 설치한 탁군(涿郡)이었고, 수(隋) 탁군의 속현으로서 계현(薊縣)이 있었다. 즉, 임삭궁(臨朔宫)이 위치했던 당(唐) 유주의 계현은 본래 수(隋) 탁군의 계현이었다. 정리하면, 고구려 침공 당시 수(隋)군은 계현을 중심으로 隋의 탁군에 집결하였다.\n\n=> 형태시의 옛 이름이 '계'다. 대청광여도에 보면 근처에 사천, 고수, 강수 등이 보인다.\n\n김진경\n연경(燕京)을 연계(燕薊)라고 지칭하고 있기 때문이다.\n즉, 상기 광양군(廣陽郡)에 속하는 계(薊)가 연경(燕京)임을 알 수 있으며 전국시대 연(燕)의 중심 지역이었음을 알 수 있다.\n요(遼) 대의 남경은 연경(燕京)이라고 불렸는데 당(唐) 대에는 유주였음을 알 수 있다. 또 『수서』지리지 권제30 탁군(涿郡)의 기록에 따르면 계(薊)는 연군(燕郡)이었는데 폐지하고 탁군을 설치하였으므로 수(隋) 대에 계(薊)는 탁군의 치소였음을 알 수 있다.\n탁주는 장치시 아래 고평시 인근 지역으로 비정할 수 있다. \n\n탁현 = 계 = 연경 = 남경\n\n\n방랑자의블로그\n(https://m.blog.naver.com/suts005/223626874636?recommendCode=2)\n대청광여도 그림의 오른쪽에 언사현(偃師)이 보이는데, \n연소공의 연나라는 섬(陝 삼문협)과 남양(南陽) 사이에 존재했다. 초기 연나라의 도읍지 燕은 황하 남쪽에 있었다.(지금의 하남 지방)\n\n북경 유리하에서 발견된 청동기에 언후(匽侯)라는 명문이 발견되어 연나라 초기 위치를 언사현이라 주장하는 중국측 주장도 있다. 중국의 주장은 문헌이 아니라 유물에 맞춰 주장하는 것이다. 청동기 명문의 匽 = 燕 이라는 주장을 하다가 안통하니 언사현(偃師), 언성현(郾城)을 들이미는 것이다.\n\n『삼국사기』지리지\n고려의 사신이 요(遼) 동경에서 요수(遼水)를 건너 하루이틀 가면 의주(醫州)에 도달하게 되고, 거기서 요(遼) 남경[南京, 연경(燕京), 연계(燕薊)]에 바로 이를 수 있다.",
  "color": "default",
  "labels": [
    "baf8ac0a-cbc0-4174-aafe-417a1cab2927",
    "51cc7fe9-2e3a-417a-8f93-7f64d0f754dc"
  ],
  "pinned": false,
  "archived": true,
  "inTrash": false,
  "reminder": null,
  "createdAt": "2024-09-07T13:33:26.375000",
  "updatedAt": "2025-03-16T14:28:20.482000"
}