{
  "id": "2cf8a89f-508a-49fa-89d0-dedc62e346b7",
  "title": "시간이란 정말 존재하는가?",
  "content": "상대성 이론으로 시간과 공간에 대해 인류가 새로운 인식을 하게 되었다고 한다. 그 구체적인 인식은 시간과 공간은 절대적이지 않으며 상대적인 것으로서 서로 의존한다는 것이다. 이 보다 더 향상된 시간에 대한 인식은, 인간이 인식하고 있는 '시간'이란 사실 실제적으로 존재하는 것이 아니라 단지 사물의 변화를 설명하기 위한 추상적인 용어일 뿐이라고 생각한다. 우주적으로 진정한 '시간'이 존재하는 지는 인간은 알 수 없다고 생각한다. 30년의 시간이 흘렀다는 것은 지구가 태양 주위를 30바퀴 돌았다는 것일 뿐이며, 어제도 오늘이고 내일도 오늘일 뿐, 어제와 오늘이 다른 점은 지구가 1도 만큼 태양 주위를 움직였다는 것이며 나의 몸의 생명력이 장기적인 평균 관점에서 다소 떨어졌다는 것이다. 그래도 위로가 되는 점은, 내가 어제보다 오늘 새로운 지식과 깨달음을 알게 되었다는 것이다. 세포가 늙어 가는 것은 몸의 재생 능력이 서서히 떨어지는 것이며 그 근원은 결국 엔트로피의 증가의 법칙 때문이므로 병이나 사고가 없더라도 몸의 전체적인 기능이 임계치 이하로 떨어지게 되면 죽게 될 것이다. 시간이 우주에 존재해야 하는 어떤 이유도 없고 있다는 증거도 없다.",
  "color": "default",
  "labels": [
    "0e59aec6-754e-4c02-893c-70f18f19c937",
    "b8f7bd7a-d946-4e58-a510-e3cdc8a3f1a6"
  ],
  "pinned": false,
  "archived": true,
  "inTrash": false,
  "reminder": null,
  "createdAt": "2023-05-19T20:19:32.328000",
  "updatedAt": "2023-05-19T20:19:32.328000"
}