{
  "id": "3c497ae3-dd7c-42b6-865c-0c78cf9777af",
  "title": "대북제제 - 임계점",
  "content": "![image](media/1559712138709.1394129946.png)\n\n\n\n임계점을 넘어야 대북제재가 효과가 있음\n\n임계점 이하로 내려오면 대북제재는 효과가 급속히 하락, \n\n- 선형이 아닌 비선형\n\n- 따라서 점진적, 단계적 타결방식은 비효율적",
  "color": "default",
  "labels": [
    "a57425d6-bf5f-4849-8870-5e88e53e4b54",
    "962773d3-36bd-4ad9-ae7c-a7d4dedcca9a",
    "bb501844-d7d7-46e2-96f8-0a8010c3c2de"
  ],
  "pinned": false,
  "archived": true,
  "inTrash": false,
  "reminder": null,
  "createdAt": "2019-03-23T18:27:01.390000",
  "updatedAt": "2023-02-11T11:17:34.384000"
}