{
  "id": "405524f6-4a13-4f6e-8ffe-98fa7b4fdce8",
  "title": "6.25 T-34",
  "content": "미군도 대전 도중에 T-34를 소련으로부터 받아 살펴본 적은 있었습니다. 그때 조사해본 자료를 토대로 보면 제원상으로는 국군과 미군의 대전차 무기들로 T-34를 격파하는게 가능했고 독일 전차들을 대상으로는 어느 정도는 먹혔던 장비들이라서 별 문제가 없다고 판단했었죠.\n실전에서는 주변 지형지물이나 운용 인원들의 숙련도, 장비 보관상태, 경사장갑 등 여러 요소로 인해 무리라는게 밝혀지기는 했지만, 실제 격파성공 사례들도 있는 걸 보면 그런 생각을 할 만도 합니다.\n거기에 한반도 지형이 전차 운용에 부적합하다고 판단한 것이 더해져서 저런 결과가 나온 겁니다.\n\n사실 전차의 효용성을 저평가한 건 소련도 똑같이 판단했었으니 미국만 욕할게 아닙니다. 소련도 전차를 지원하기는 했지만 마찬가지로 한반도가 전차를 운용하기에 부적합하다고  판단해서 북한에 대한 전차지원을 축소하고 그 분량 만큼을 항공기 지원으로 대체한 바가 있어요. 실제로 적합한 지형이 아니라서 서울로 진격하던 북한군 전차가 길을 통과할 수가 없어서 다시 되돌아 가다 후속부대랑 뒤섞여 진격이 지연된 사례도 있었고,  무리한 기동으로 부품의 소모가 극심해 기동불가 상태가 된 전차들을 분해해 다른 전차들을 수리하는데 쓰기도 했습니다.",
  "color": "default",
  "labels": [
    "7614a8cc-7612-44a0-80ce-fcaffc04867d",
    "d681d9ed-1ad5-4666-a9d4-269e4225597d"
  ],
  "pinned": false,
  "archived": true,
  "inTrash": false,
  "reminder": null,
  "createdAt": "2022-02-14T08:51:55.374000",
  "updatedAt": "2022-02-23T10:38:15.655000"
}