{
  "id": "50fcfefb-e8e1-4f84-93cb-12cd9775cd35",
  "title": "폭격의 역사",
  "content": "나가사키와 히로시마에서 두 발의 핵폭탄을 사용한 폭격보다 더 무서운 폭격을 진행한 바 있다. \n2차 세계대전에는 미국과 영국이 독일 드레스덴에 3일 동안 3000 톤 이상의 폭격을 가해서 3만 명 가까운 인명이 사망한 사례가 그것. \n\n도쿄 대공습에서 미국은 2400톤 이상의 폭격을 가해서 10만 명이 사망한 경우도 있었다. 그럼에도 나치 독일과 일본제국은 대폭격으로 전쟁을 단념하지 않았다. \n\n북한 역시 한국전쟁 때 평양에만 47만 발의 폭탄으로 폭격 받았지만 전쟁이 끝나지 않았다.",
  "color": "default",
  "labels": [
    "7614a8cc-7612-44a0-80ce-fcaffc04867d",
    "d681d9ed-1ad5-4666-a9d4-269e4225597d"
  ],
  "pinned": false,
  "archived": true,
  "inTrash": false,
  "reminder": null,
  "createdAt": "2023-10-05T09:04:14.982000",
  "updatedAt": "2023-10-05T09:07:23.799000"
}