{
  "id": "5e169dc6-e5eb-4857-911e-00c490246298",
  "title": "상춘(常春)",
  "content": "![image](media/1764461810802.993219854.png)\n![image](media/1764461891987.1841291775.png)\n\n\n[조선(朝鮮) 제6대 달문(達門) 천왕의 역사] \n서기전2049년 임자년(壬子年)에 모든 한(汗)들을 상춘(常春)에 모이도록 하여 구월산(九月山)에서 삼신(三神)께 제(祭)를 올렸는데, 신지(神誌) 발리(發理)로 하여금 서효사(誓效詞)를 짓게 하였다.  \n\n고대 한국사: '상춘(常春)'은 고대 한국에서 '늘봄'이라는 뜻을 가진 '눌견(訥見)'의 한자식 표기입니다.\n단군조선 시기: 『환단고기』 등 일부 문헌에 따르면, 단군조선 제6대 달문 단군이 여러 제후들을 상춘에 모아 구월산에서 삼신(三神)께 천제를 지냈다는 기록이 있습니다.\n고구려 시기: 고구려 시조 주몽(동명성왕)이 초기 도읍지인 졸본에서 '눌현'(상춘)으로 도읍을 옮겼다는 기록이 『태백일사』 등의 문헌에 전해집니다.\n현재 위치: 이 상춘 지역은 현재 중국 지린성(길림성)의 장춘(長春, 창춘) 지역으로 비정되며, 그 북쪽에 주몽의 성터인 '주성자(朱城子)'라는 지명이 남아있다고 합니다",
  "color": "default",
  "labels": [],
  "pinned": false,
  "archived": true,
  "inTrash": false,
  "reminder": null,
  "createdAt": "2025-11-30T09:13:17.771000",
  "updatedAt": "2025-11-30T09:19:38.611000"
}