{
  "id": "695adc2a-18e3-4c8c-be8f-baa302bba7bf",
  "title": "앤서니 다운스",
  "content": "<경제이론으로 본 민주주의>에서 앤서니 다운스는 두 가지 획기적인 가설을 내세웠다. 즉, 관료와 정치가는 장사꾼과 마찬가지로 사익을 추구하는 존재라는 가설과 시장의 논리가 지배하는 민주주의 사회에서 정치에 대한 국민의 무관심과 낮은 투표율은 당연하다는 요지의 ‘합리적 무지’ 가설이다.\n\n다운스의 후학들은 정경유착(정확하게 말하면 지대추구), 부처이기주의, 관료의 예산극대화 행태 등을 파헤치면서 ‘정부의 실패’와 ‘정치의 실패’에 대한 체계적 이론을 구축했다.\n\n다운스의 <경제이론으로 본 민주주의>가 주는 한 가지 교훈은, 배신당하지 않기 위해서는 국민이 높은 정치의식을 갖고, 정부와 정치가를 철저히 감시, 감독해야 한다는 것이다.",
  "color": "default",
  "labels": [
    "898f43eb-c79c-4781-9c09-9e88a458c8c7",
    "bb501844-d7d7-46e2-96f8-0a8010c3c2de"
  ],
  "pinned": false,
  "archived": true,
  "inTrash": false,
  "reminder": null,
  "createdAt": "2022-10-11T18:04:06.278000",
  "updatedAt": "2024-12-21T19:34:21.521000"
}