{
  "id": "75cf0911-22b0-4663-835b-381daa444c8b",
  "title": "혼합전략(교란전술)",
  "content": "단일전략으로 내쉬균형이 없는 게임\n\n여러 전략을 확률적으로 선택하는 혼합전략 내쉬균형\n\n오락게임은 내쉬균형이 없는 것이 오락성을 높임.\n오락게임에 내쉬균형이 있다면 금방 결론이 나기 때문에 재미 없음.\n\n예측 가능한 일관된 행동을 삼가라\ndo not repeat same pattern!\n\n혼합전략에서 전략의 가지수가 증가하는 것이 상대방의 적중율을 낮춰 유리하다.\n\n예) 가위,바위,보 게임 -> 가위 잽이, 바위 잽이, 보 잽이가 되서는 안된다.\n\n예) 코소보 사태 때 f-117 스텔스기 격추 : f-117이 매번 같은 경로로 다니므로 sa-3 근거리 지대공미사일(사정거리 20km)이 길목을 지키다가 격추, 1960년 정찰기 U-2 소련상공에서 격추\n\n예) 모형(비행기, 탱크 등)과 실제의 혼합배치, 모형(디코이) 미사일 발사대와 실제 미사일 발사대의 혼합배치, 베트남전 당시 베트남의 SA-75 혼합 배치\n\n\n에) 스타크래프트 전략  :  같은 전략을 계속 쓰면 상대방의 대응전략에 막힘\n\n예) 투수의 볼 배합(왼쪽, 오른쪽, 위쪽, 아랫쪽, 커브, 시커, 슬라이더, 커터, 직구), \n승부차기시 골의 방향(좌, 중앙, 우), \n과속 감시카메라 위치 변경, \n임의로 출석 체크\n\n예) 걸프전이나 이라크전에서 상륙작전이 있진 않았지만 미군이 훼이크로 사용해서 이라크군이 어쩔수 없이 해안쪽에 부대를 상당수 배치해서 주력군이 진격하는데 큰 기여를 했다고 합니다. 즉 상륙능력을 갖추는건 다양한 전략적 선택권을 줄수 있다고 최근 잡지에서 많이 소개되긴 했져..\"해병대 상륙능력 보유하게 되면 상대 수비가 약하면 진짜 상륙작전을 펼칠수 있고..상륙작전은 못 펼치더라도 상대의 주력을 상당부분 해안으로 묶을수 있다\"\n\n예) 포티튜드 작전 : 노르망디 상륙작전 기만",
  "color": "default",
  "labels": [
    "4c2e72b8-0cf2-48f3-b5fa-5ad39f6b68ea"
  ],
  "pinned": false,
  "archived": true,
  "inTrash": false,
  "reminder": null,
  "createdAt": "2019-03-03T18:36:18.927000",
  "updatedAt": "2023-08-26T23:13:25.723000"
}