{
  "id": "8064335a-5cb7-4787-b34f-93057f078a13",
  "title": "고려 문주/고주",
  "content": "![image](media/19504c90609.9d94898d3b591308.png)\n![image](media/19504cd3ddf.a8fd71dcaf3fcc83.png)\n![image](media/19b71decba8.8595185657dacbfb.jpg)\n\n\n옛 명칭은 매성(妹城) 또는 이균성(伊均城)이었는데, 989년(성종 8) 성(城)을 쌓고 문주로 칭하여 방어사(防禦使)를 두었으며 동계(東界)에 예속시켰다. 뒤에 의주(宜州)에 합쳤고, 1345년(충목왕 1) 이를 다시 나누어 지문주사(知文州事)로 하였다. 1413년(태종 13)문천군으로 바꾸었으며, 치소(治所)를 동쪽의 아미산(峨眉山) 부근으로 옮겼다.\n아미산 동쪽의 차파령(車破嶺)에는 고산성(古山城)이 있고, 조선시대에는 부근에 양기역(良驥驛)이 있었으며, 북쪽의 천달산(天達山)에는 봉수가 있어 남쪽의 소달산(所達山) 봉수와 연결되었고, 서남쪽의 노달령(蘆達嶺)을 넘어 금강산에 이르게 된다. 고려시대 몽고병의 침입이 있었고, 북부의 국경 요새로서 군사적인 시설이 많았다.\n\n\n용진진(龍津鎭)은 옛날의 호포(狐浦)로, 고려 초에 지금 이름으로 고쳐 진(鎭)으로 삼았다. 목종 9년(1006)에 성을 쌓았다. 뒤에 문주(文州)에 소속시켰다. 우왕 5년(1379)에 다시 분리해 현령(縣令)을 두었다. 별호(別號)는 용성(龍城)이다.\n\n\n고원군(高原郡)\n지군사(知郡事)가 1인이니, 영흥도 우익 병마(永興道右翼兵馬)를 겸한다. 옛날에는 덕령진(德寧鎭)이라 하였었는데, 고려 광종(光宗) 24년에 비로소 성을 쌓았고, 현종(顯宗) 때 고주 방어사(高州防禦使)로 고치었다가, 공민왕(恭愍王) 5년에 지고주사(知高州事)로 삼았으며, 본조 태종 13년에 예에 따라 지금의 이름으로 고쳤다. 속진(屬鎭)이 1이니, 애수(隘守)이다. 옛날에는 이병(梨柄)이라 하였는데, 고려 성종(成宗) 2년에 비로소 성을 쌓았다. 본래 문주(文州)에 예속되었으나, 공민왕(恭愍王) 9년에 본국에 내속시켰으며, 지금도 그대로 진(鎭)이라 일컫는다.",
  "color": "default",
  "labels": [
    "d681d9ed-1ad5-4666-a9d4-269e4225597d"
  ],
  "pinned": false,
  "archived": true,
  "inTrash": false,
  "reminder": null,
  "createdAt": "2024-06-20T06:35:26.101000",
  "updatedAt": "2025-12-31T09:47:49.030000"
}