{
  "id": "908684d3-c75c-4d2f-8587-014b664ec4f3",
  "title": "영주(寧州)/안북대도호부/청천강",
  "content": "![image](media/1911af79474.87816d02eb323227.jpg)\n![image](media/1998c07a52f.9907d341dfd4ba0e.jpg)\n![image](media/1998c0ac87d.a893c25cf3746c41.png)\n![image](media/19b14e8e26d.b90a120e6cab5758.jpg)\n\n\n안북대도호부(安北大都護府) 영주(寧州)는 본래 고려의 팽원군(彭原郡)이다. \n태조 14년(931)에 안북부(安北府)를 두었다. \n성종 2년(983)에 영주(寧州) 안북대도호부(安北大都護府)라고 불렀다. \n현종 9년(1018)에 안북대도호부(安北大都護府)라고 불렀다. \n고종 43년(1256)에 몽고 병사를 피해 창린도(昌麟島)에 들어갔다가 뒤에 육지로 나왔다. \n공민왕 18년(1369)에 안주만호부(安州萬戶府)를 두었다. 뒤에 목(牧)으로 승격시켰다. 별호(別號)는 안릉(安陵)이고【성종[成廟] 때 정하였다.】, 청천강(淸川江)이 있다【옛날에 살수(薩水)라고 불렀는데, 곧 고구려 을지문덕(乙支文德)이 수(隋)나라 병사 1,000,000명을 격퇴한 곳이다.】. 관할하는 방어군(防禦郡)이 25개이고, 진(鎭)이 12개이고, 현(縣)이 6개이다.\n\n\n營州와 平州는 섬서성 포성현과 백수현 일대가 된다. \n이는 고구려 시대이며 9세기 원화군현지가 나온 이후에는 하북성 보정시쪽으로 지명이 이동되며 통전으로 이를 고착시키었다. 명나라는  현 북경시 동쪽으로 이동시켰다.\n\n대명고성\n\n은허(殷墟)\n왕실 무덤군: 상나라 왕과 귀족들의 대형 무덤이 있습니다. 그 중 부호(妇好) 무덤은 상나라 중기 여장군이었던 부호의 무덤으로, 미라가 아닌 유골과 함께 수많은 청동기, 옥기, 토기 등이 거의 완벽하게 보존된 채로 발견되어 세상을 놀라게 했습니다.\n\n安阳城遗址 (Anyang Cheng Ruins / 안양성 유적)\n이것은 춘추전국시대(春秋戰國) 시절의 안양성 유적지로, 현재 안양시의 일부 구역에 존재하는 고대 성터입니다. 현재 남아 있는 것은 동쪽 성벽 일부가 가장 뚜렷하며, 나머지 부분은 흔적만 남아 있는 상태입니다.\n\n安阳故城\n即西汉时期的新阳县城（汉成帝鸿嘉二年封顷侯永于新阳）。位于邹坞镇南安阳村北。故城地处台型高地，四面墙基清晰可见，东、西、南三面尤为明显，有的地段竟高出地表4—5米，均系黄土夯筑而成。城周长约1000米，总面积约6000平方米。故城内，地面上散见许多陶器残片，有灰陶、红陶，而灰陶居多。1993年被枣庄市人民政府公布为市级重点文物保护单位，2006年被山东省人民政府公布为第三批文物保护单位。\n邹坞镇：枣庄市薛城区辖镇。1960年建邹坞公社，1984年设邹坞镇。位于区境东部，距市中心10公里。面积60平方公里，人口4.5万。枣薛铁路、枣薛公路、枣木高速公路过境。辖西邹坞、西南、西北、龚庄、东邹坞、小甘林、南陈郝、庄头、肖村、岩埠、南安阳、姚庄、打席、洪村、罗岭、北陈郝、官庄、东山口、张岭、刘庄、中陈郝、张庄、北安阳、东尚庄、西尚庄、西山口、刘沟、墓山、周村…… 邹坞镇详细信息++\n延伸阅读：",
  "color": "default",
  "labels": [
    "51cc7fe9-2e3a-417a-8f93-7f64d0f754dc"
  ],
  "pinned": false,
  "archived": true,
  "inTrash": false,
  "reminder": null,
  "createdAt": "2024-08-04T10:17:11.801000",
  "updatedAt": "2025-12-13T09:07:01.044000"
}