{
  "id": "945227ab-abad-49c6-83af-5ca21881c476",
  "title": "한국의 수도권 집중",
  "content": "![image](media/1760491623793.2037994648.png)\n![image](media/1760493519641.1520619504.png)\n\n\n\n\n한국은 국가 인구의 절반 이상이 수도권에 집중, OECD 국가 중 가장 높은 수준의 수도권 집중도를 기록하고 있습니다.\n일본 도쿄권도 세계 최대 도시권이지만, 국토가 크고 지방 거점도시들이 살아있기 때문에 상대적으로 완화되어 있습니다.\n중국은 베이징보다 상하이·선전·광저우 등 다핵 구조이므로,  정치적 수도 집중은 강하지만 경제적 집중은 분산형입니다.\n유럽(특히 프랑스·영국)은 역사적으로 수도 집중 현상이 있었지만,  현재는 지방분권 정책과 교통 인프라 발달로 완화 추세입니다.\n\n서울 수도권 집중도는 세계 최상위 수준으로 인구 비중으로 보면 파리·도쿄보다 높고, 경제 기능까지 고려하면 한국은 ‘단일 도시국가형 구조’ 에 가깝습니다.\n이런 구조는 효율성 측면에서는 강점이지만,  지방 소멸·부동산 과열·교통 혼잡·청년 인구 쏠림 같은 심각한 부작용을 동반합니다.\n\n=======================================================\n\n 원인은 단순히 부동산 문제를 넘어서,  정치·경제·사회·문화 전반의 구조적 결과입니다.\n “전후 압축성장 + 중앙집권 행정 + 산업·교육의 수도권 편중 + 지방의 기회 결핍”\n 이 네 가지가 서로 피드백을 일으키며 수도권 집중을 가속시킨 결과입니다.\n\n1. 강한 중앙집권 행정 구조\n한국은 1960년대 이후 행정·재정 권한이 서울 중앙정부에 집중되었습니다.\n주요 부처·공공기관·국영기업 대부분이 서울에 위치했고,  각종 정책 결정·예산 배분이 서울 중심으로 이루어짐.\n“정책의 수도권 편향 → 일자리·산업 집중 → 인구 유입 → 정치적 영향력 강화”라는 순환 고리가 형성됨.\n지방정부의 자율재정 비율이 OECD 최하위권(약 30%) 수준이라  지방이 독립적으로 발전 전략을 세우기 어려움.\n\n📍요약: 행정집중이 모든 집중의 뿌리.\n\n2. 산업화 과정에서의 수도권 우선 성장 전략\n1960~80년대 경제개발 5개년 계획은 “효율적 자본 배분”을 명목으로   교통·항만·금융 인프라를 수도권에 집중시킴.\n경공업·전자·서비스업 중심의 산업 구조는 고급 인력·소비시장 근접성을 요구했기에,\n 서울과 인근 지역(경기, 인천)에 산업벨트가 형성됨.\n1970년대 중화학 공업화 정책이 울산·포항·창원 등 지방에 추진되었지만,\n 연구·본사·금융·행정 기능은 여전히 서울에 남아 “본사-공장 분리 구조”를 고착화.\n\n📍요약: 산업의 심장은 서울, 지방은 팔과 다리.\n\n3. 교육·고용 기회의 수도권 집중\n서울에는 상위권 대학의 80% 이상,   그리고 대기업 본사의 70% 이상이 집중되어 있음.\n좋은 대학 → 좋은 일자리 → 수도권 정착이라는 ‘인재의 경로 의존 경로(path-dependence)’가 형성됨.\n지방에서 공부 잘하는 학생일수록 서울로 가고,  그들이 다시 지방으로 돌아가지 않음 → 지방 인재 유출(Brain Drain).\n이는 지방 청년층 감소 → 지방 소비 감소 → 기업 유입 부진으로 이어지는 악순환.\n\n📍요약: 교육과 일자리의 수도권 독점이 인구를 빨아들임.\n\n4. 부동산·금융자본의 수도권 집중\n자산 가치 상승 기대가 서울 부동산에 집중되면서  부동산-금융-정치권의 이익 연합 구조가 형성됨.\n지방 부동산은 투자 매력도가 낮아지고,  개인 자산 축적의 경로가 “서울 아파트”로 고정됨.\n금융기관 본점·투자자본 대부분이 서울에 집중되어  지역 경제의 자금 순환이 수도권 중심으로 편향됨.\n\n📍요약: 서울 부동산이 ‘국가적 자산 저장소’로 기능.\n\n 5. 지방 생활 인프라의 상대적 낙후\n의료, 문화, 교통, 교육 인프라의 질 차이가 커서  중산층 이상은 지방에 정착하기 어렵다고 느낌.\n예: 지방 대도시의 병원·학교·공공서비스 접근성이 서울의 60~70% 수준.\n지방 도시 간 연결망이 약하고, 내륙 중심의 균형발전 축이 형성되지 않음.\n\n📍요약: “살 만한 지방”이 많지 않음.\n\n 6. 정치적·사회적 피드백 루프\n수도권 인구가 전체 유권자의 절반 이상 →  선거 전략이 수도권 중심으로 짜임 →  정치·예산이 수도권으로 더 집중 →  다시 인구가 몰리는 자기강화(Self-reinforcing) 구조.\n중앙정부·국회·언론·문화 산업이 모두 서울에 모여 있어서   “서울 중심 세계관”이 국가 의사결정을 지배.\n\n📍요약: 정치적 힘의 편중이 경제적 집중을 되먹임.\n\n행정 집중  → 산업·교육 집중  → 인구 집중  → 정치적 영향력 강화  → 예산·정책 수도권 편향  → 다시 행정집중\n\n이 순환이 60년간 반복되며 자기강화적 수도권 구조(path-dependent equilibrium)가 굳어짐.\n\n7. 결론\n 한국의 수도권 집중은 “정책 실패” 이전에 “국가 설계의 구조적 귀결”이다.\n 행정·산업·교육·자산이 모두 서울을 중심으로 얽힌 복합적 경로 의존 현상이며,  이를 해소하려면 단순한 지방 이전이 아니라 행정·산업·금융의 권력 구조 자체를 분산시키는 체제 개편이 필요합니다.\n\n==========================================\n\n왜 중국 쪽은 하락하는 반면, 서울은 계속 오르는가 하는 점에서는 몇 가지 차이점이 있어요:\n\n중국은 과잉 공급 + 개발사 부채 리스크 + 심리 위축이 강한 반면,  한국 서울은 아직 수요가 공급을 초과하는 구조\n중국 정부는 상당히 강력한 개입 및 규제를 지속해 왔고, 일부 지역은 규제 완화에도 시장이 반응하지 않는 반면,  한국은 완전히 규제를 푸는 것은 아니지만 정책 기대감 변화가 시장 심리에 더 민감하게 작용\n중국은 인구 구조 변화, 도시화 둔화 등의 요인이 더 강하게 작용할 여지가 큰 반면, 한국 수도권 집중 현상이 상대적으로 덜 완화됨\n\n현재 시점에서는 한국의 수도권 집중 현상이 중국보다 훨씬 더 심하다”고 보는 것이 맞습니다. 다만, 중국은 물리적 규모가 워낙 크고 행정구역 단위가 넓기 때문에  절대적인 인구 수로는 비교가 어렵지만,  비율(집중도)로 보면 한국이 중국보다 훨씬 극단적인 형태의 수도권 집중 구조를 가지고 있습니다.\n\n한국의 수도권 집중 정도 \n◆ 수도권 인구 비중 (서울·경기·인천) \n약 2,650만 명 / 전국 5,200만 명 → 약 51% (통계청, 2025년) \n인구의 절반 이상이 수도권에 거주\n\n◆ 경제 생산 비중(GRDP 기준) \n수도권이 전국 GDP의 55~60% 차지\n산업·서비스 중심 기능의 과도한 집중\n\n◆ 대학·병원·문화시설 집중도\n주요 상위권 대학의 80% 이상이 수도권에 위치\n교육·문화·고용 기회가 집중되어 인구 쏠림을 강화\n\n◆ 교통망 구조\n수도권 방사형 구조 (서울 중심)\n전국 교통망이 수도권으로 수렴하는 형태\n\n==> 한국은 국가 전체가 사실상 하나의 거대 수도권(Mega-Seoul) 으로 수렴하고 있습니다.\n\n\n중국의 대도시 집중 구조\n중국은 수도권 집중이 아닌 ‘다중 중심 다핵형 구조’(multi-core system) 로 되어 있습니다.\n\n징진지권 (京津冀)\n베이징·톈진·허베이\n약 1.1억 명 (전국의 8%)\n수도권 기능 있으나 상대적으로 분산\n\n장강삼각주권 (长三角)\n상하이·항저우·쑤저우 등\n약 2.3억 명 (16%)\n경제력 중심지\n\n주강삼각주권 (珠三角)\n광저우·선전·홍콩\n약 1.2억 명 (8%)\n수출·금융 중심\n\n성도·충칭·우한 등 내륙권\n약 3억 명 이상\n지방 대도시들이 자립적 발전 구조 유지\n\n즉, 중국은 수도권(베이징권) 하나가 아니라  여러 대도시권이 분산되어 발전하는 구조입니다.  이는 국가 크기와 분권형 행정 구조, 지역 산업 다양성 덕분입니다.\n\n분석 요약\n한국은 단일 수도권 의존형 경제 구조,\n중국은 복수 핵심 도시가 경쟁·보완하는 분산형 구조.\n따라서 한국은 인구·산업·교육·문화·정치 기능이 모두 서울 중심으로 몰린 초집중형 국가,\n 반면 중국은 국가 단위로 보면 ‘수도권 집중’보다는 ‘도시권 경쟁 구조’ 에 가깝습니다.\n\n===================================\n\n부산에 뭐 일자리가 있어야 남을지 말지 고민이라도 하는데 투표 ㅈ같이 해서 부산에 공단이 싹 빠져나간지도 오래고 괜찮은 일자리가 씨가 마름\n\n가끔 이렇게 투표탓 하시는분도 계시는데\n물론 그게 영향이 없진 않겠지만 다른 지역들도 비슷한 상황임.. 언론에 조명되는곳이 경상도 지역들이니까 욕하고 마는데 전라도 강원도 진짜 처참함\n\n노통이 새종시 이전 하자고 할때 옮겼으면 이정도는 아녔을텐데 관습헌법이라는 희대의 쌉소리를 남긴 재판부..\n\n그게 우리나라 산소호흡기에 말뚝 박은거라고 생각함..\n\n그때 수도 옮겨서 출산율 0.8까지 안떨어지고 1.2 정도 갔다고 쳐도 언론이 1.5에서 떨어졌다고 실패한 정책이라고 결론 냈을거임 언론개혁 안하면 성공한 정책도 실패한 정책이 됨\n\n지금이라도 서초동 법원 검찰청 전부 세종으로 옮기면 지금보다는 나아질 것 같네요. 예전에 강북에서 강남으로 옮길 때 끝까지 법원이 버티다 강제 이전당했는데, 부유층과 고위층의 이전 완료로 강남 르네상스의 정점을 찍었다고 하네요.\n\n\n한국은행의 '지역간 인구이동과 지역경제' 자료를 살펴보면 2015년부터 2021까지 수도권 인구 증가에 대한 청년층 유입의 기여율은 78.5%에 달한다. 반대로 인구가 감소한 동남권, 호남권, 대경권에선 청년 유출의 기여율이 각각 75.3%, 87.8%, 77.2%로 집계됐다.\n이로 인해 호남권은 청년층 유출에 따른 출산 손실이 49.7%, 대경권·동남권도 각각 31.6%·21.9%에 달했다. 이처럼 지방소멸 요인 중 하나인 청년층 유출은 △의료 공백 △교육 기회 부족 △교통 불편 △양질의 일자리 부족 등의 격차가 결정적이다.\nhttps://www.nocutnews.co.kr/news/6358405\n\n\n영암인가 영광에 원전있습니다\n전라도가 친환경발전을 계속 밀어서 태양광이랑 풍력 발전으로 전기가 남아돌기는 합니다\n공장짓기에는 가장 좋은 조건은 맞는데 공장들이 인재때문에 수도권서 내려가길 꺼려하죠\n원전이 동해에 치우친건 그런거 때문이 아니고 한반도는 편서풍이 불기 때문에 혹시나 사고나면 원전분진이 한반도를 훝고 지나가기 때문입니다.\n요즘은 원전 안정성이 보증되서 의미없긴하지만\n백퍼 예상 드리는게 투자가 지속안될 확률이 100%임\n중간에 계획틀어질 확률이 높음.\n평택 P1 삽뜰때부터 있었는데 평택도 첨 계획에서 많이 달라졌음\n용인도 중간에 멈출확률이 매우 높고 전기, 물 때문에 지연될 확률 백퍼임\n전기야 발전소 건설하면 되긴하는데 주변지역에 다 반대중이라 한참 걸릴거고 문제는 물인데 답이 읍슴\n\n새만금은 매립지라 지반이약해서 라인은 어차피 못들어갑니다.\n\n이미 리튬 배터리 공장들은 다 들어왔어요. 딱히 문제가 안되나보더군요.",
  "color": "default",
  "labels": [
    "898f43eb-c79c-4781-9c09-9e88a458c8c7",
    "a57425d6-bf5f-4849-8870-5e88e53e4b54",
    "bb501844-d7d7-46e2-96f8-0a8010c3c2de",
    "f1a3f248-23d9-40f7-9015-108e250fc2dc",
    "8a2c08db-2799-4365-9a30-76f7fb30e0c0"
  ],
  "pinned": false,
  "archived": true,
  "inTrash": false,
  "reminder": null,
  "createdAt": "2025-10-15T10:07:17.097000",
  "updatedAt": "2026-01-01T09:23:20.335000"
}