{
  "id": "97edf074-aab7-428f-8b1f-c3d3f5ae0787",
  "title": "유인제도(incentive system)",
  "content": "상앙은 ‘왕도나 예법보다는 법에 의한 통치’를 강조했다. 능력과 성과에 기초한 보상 체계인 이십등군공작제(二十等軍功爵制) 등 과감한 개혁을 밀어붙였다. 상앙은 군사적 공적을 세운 자에게 벼슬을 주는 ‘20등작(等爵) 제도’를 시행했다. \n\n상앙은 이렇게 규정했다. 진나라의 사병이 적의 수급 1개를 획득하면, 바로 작위 1급을 획득하고, 밭과 집 1채 및 노비 몇명을 얻는다. 죽인 적군의 수급이 많을수록 받는 작위는 더욱 높아진다. 전쟁에서 잘 싸우기만 하면 작위를 받을 수 있고, 작위를 받으면 토지도 가지고 집도 얻게 된다. 결국 모든 생활은 싸움을 얼마나 잘하느냐에 달려있는 것이다. 이것이 바로 상앙의 유명한 \"군공수작제도(軍功授爵制度)\"이다.\n군공에 따라 나뉘어진 등급은 엄격하게 적용되었고, 진의 사병들은 군공을 세우려는 갈망에 가득차 있었다.\n그 이전에는 오직 귀족들만 벼슬을 할 수 있었다. 귀족에게만 세습적으로 벼슬을 독점하는 권한이 주어져 있었을 뿐 일반 서민들에게 벼슬은 꿈도 꾸지 못할 대상이었다. 하지만 상앙의 개혁은 누구든 신분의 고하를 막론하고 군공(軍功)을 세우면 신분 상승의 기회를 제공하였고, 이런 기회를 쟁취하기 위하여 일반 평민들은 몸을 사리지 않고 전쟁에 앞장서게 되었다. 반면 군주의 친척이라도 군공이 없으면 심사를 거쳐 족보에 올릴 수 없게 했으며, 전공(戰功)이 없는 사람은 비록 부유할지라도 영예를 과시할 수 없었다. \n상앙의 이러한 정책은 진나라 군사체제를 획기적으로 강화시킴으로써 이후 진나라는 급속하게 강대국으로 성장할 수 있었다.",
  "color": "default",
  "labels": [
    "898f43eb-c79c-4781-9c09-9e88a458c8c7",
    "d681d9ed-1ad5-4666-a9d4-269e4225597d",
    "4c2e72b8-0cf2-48f3-b5fa-5ad39f6b68ea"
  ],
  "pinned": false,
  "archived": true,
  "inTrash": false,
  "reminder": null,
  "createdAt": "2022-05-25T10:41:36.366000",
  "updatedAt": "2023-03-30T19:57:44.821000"
}