{
  "id": "b39eb3e1-89cc-41cb-9c06-14806e132dcd",
  "title": "유보트",
  "content": "유보트의 천적이 항모란게 알려지면서 유보트의 활약은 힘들게 됐죠.\n당시 유보트는 깊게 잠수할 수 없어서 정찰기기 날라가면서 보면 다 보였답니다.\n발견 되면 구축함이 와서 폭뢰 꽝.\n그래서 경항모에 정찰기 싣고 구축함이 상선단과 같이 다니면 유보트는 할게 없었죠.\n\n결국 내연기관의 한계로 잠항시간이 짧았기 때문인 것으로 압니다.\n잠항을 위해서는 전기 축전지의 힘으로 잠항을 할 수 있었는데 그 시간이 매우 짧았다죠.\n그래서 디젤기관으로 운행을 해서 늘 축전지를 충전해야 했기 때문에 스노클을 밖에 내야 해서 깊이 잠수 할 수 없었던 것으로 압니다.\n물론 나중에 조금 개선이 되자 이번에는 소나가 괴롭히게 되죠.\n\n소나는 유보트 활동 초기부터 발명 되어 있었고요.\n단지 대잠 전술이 확립되지 않았죠.\n유보트가 심해잠수를 해버리면 도망간줄 알고 그냥 지나쳐 버렸으니까요.\n유보트는 심해잠수를 해버리면 움직이지도 못하고 오래 잠수해 있지도 못한다는걸 몰았으니까요.\n오래 잠수를 못하는 이유도 내구도 때문입니다. 수압을 버티질 못해요.\n하지만 잠수하면 그자리에서 기다리면 다시 올라온다는걸 알게 되면서 유보트는 지옥이 펼쳐졌죠.",
  "color": "default",
  "labels": [
    "7614a8cc-7612-44a0-80ce-fcaffc04867d"
  ],
  "pinned": false,
  "archived": true,
  "inTrash": false,
  "reminder": null,
  "createdAt": "2022-05-10T13:58:02.933000",
  "updatedAt": "2022-05-10T13:58:02.933000"
}