{
  "id": "cc185feb-fd2c-491a-8eab-debdc6b5b27f",
  "title": "패러데이의 새장(Faraday cage)  원리",
  "content": "전도성 물질로 만들어진 물체의 내부에는 외부로부터 가해지는 전기장이 완벽히 차단된다는 원리이다. 천둥 번개가 칠 때, 자동차나 비행기 안에 있으면 천둥 번개로부터 안전하다는 것이 대표적인 예다.\n패러데이 새장의 작용은 외부 정전기장이 새장 도체 속의 전하를 재배치시킴으로써 장의 효과가 새장의 내부에 미치지 않게 되어 발생한다. 이 현상은 예를 들면 전자 장치를 번개나 기타 방전으로부터 보호하기 위해 사용된다.\n\n비행기에 번개가 치면 표면의 두랄루민과 정전기 방출기 덕분에 전류가 표현으로 흐른 뒤 날개 끝에서 다시 공중으로 흩어지게 됩니다.\n\n전자레인지 속 전화벨이 울리지 않는 것은 전자레인지가 모든 전자파를 완벽히 차단하고 있다는 것이며, 밖으로도 새어 나가지 않는다는 말이다.\n\n EMP공격에 대비로 알루미늄 호일로 감싸는 걸로 방호 가능. \n 라디오, 손전등, 휴대폰 이런 거 알루미늄 호일로 감싸놓으삼. 작은 전자기기들은 EMP 방호 쉬움",
  "color": "default",
  "labels": [
    "7614a8cc-7612-44a0-80ce-fcaffc04867d",
    "0e59aec6-754e-4c02-893c-70f18f19c937",
    "9dde1e04-dd34-4201-bce0-c559b528d7a5"
  ],
  "pinned": false,
  "archived": true,
  "inTrash": false,
  "reminder": null,
  "createdAt": "2023-10-20T08:02:34.818000",
  "updatedAt": "2023-10-20T08:29:14.049000"
}