{
  "id": "d7e7e8f1-254c-446a-a989-b8ccbbe84376",
  "title": "아베 노부유키",
  "content": "조선총독부 마지막 총독 ‘아베 노부유키’가 조선을 떠나며 했던 말\n\n“우리는 패했지만 조선은 승리한 것이 아니다. 장담하건데, 조선민이 제 정신을 차리고 찬란하고 위대했던 옛 조선의 영광을 되찾으려면 100년이라는 세월이 훨씬 걸릴 것이다. 우리 일본은 조선민에게 총과 대포보다 무서운 식민교육을 심어 놓았다. 결국은 서로 이간질하며 노예적 삶을 살 것이다. 보라! 실로 조선은 위대했고 찬란했지만 현재 조선은 결국 식민교육의 노예로 전락할 것이다. 그리고 나 아베 노부유키는 다시 돌아온다.” \n                                 - 아베 노부유키 연설 中",
  "color": "default",
  "labels": [
    "d681d9ed-1ad5-4666-a9d4-269e4225597d",
    "518afb00-3f62-4da5-9663-d9ad9708e63f"
  ],
  "pinned": false,
  "archived": true,
  "inTrash": false,
  "reminder": null,
  "createdAt": "2024-07-23T10:03:24.112000",
  "updatedAt": "2025-09-19T12:33:29.640000"
}