{
  "id": "d8d61317-d07f-4480-ae7a-010dbc6143c3",
  "title": "정치적 경쟁",
  "content": "경제 시장과 같이 정치판에도 경쟁이 필요. 다당제 문화\n야당의 정부 정책에 대한 비판은 개선, 국가 발전, 개량에 도움을 줌. 견제구 역활, 채찍질 역활\n독재 국가에서는 귄력자/왕에 대한 비판이 없음. 국가 발전의 기회가 적음",
  "color": "default",
  "labels": [
    "898f43eb-c79c-4781-9c09-9e88a458c8c7",
    "bb501844-d7d7-46e2-96f8-0a8010c3c2de"
  ],
  "pinned": false,
  "archived": true,
  "inTrash": false,
  "reminder": null,
  "createdAt": "2022-12-31T13:32:39.966000",
  "updatedAt": "2022-12-31T13:32:39.966000"
}