{
  "id": "f588f660-0c98-4bb6-a085-e34ec02f2f90",
  "title": "낙양(낙읍)의 위치\n",
  "content": "![image](media/18ffcd3f994.84b1798a0a514c5b.jpg)\n![image](media/1904a74e0a7.84bffd67b9cf1c7f.png)\n![image](media/190573a2501.9de7cb2b32fc5112.png)\n![image](media/190fad7c82f.b9d993b53b2200d2.jpg)\n![image](media/1912f0723e4.863c60efafd2f084.jpg)\n![image](media/19b442a914e.bc8dc6b25b0876a2.png)\n![image](media/19b44315a39.9a4ca9e37479811f.jpg)\n![image](media/19b44315a49.bc235dec6bafaf8f.jpg)\n![image](media/19b44315a58.9f6ad9a7ce873a02.jpg)\n![image](media/19b44315a65.98485f43ddd96ad6.jpg)\n![image](media/19b44315a74.a588b924abaa0017.jpg)\n![image](media/19b44315a81.907f581e9077ba3b.jpg)\n![image](media/19b44315a8f.9ca86fb9e146969f.jpg)\n![image](media/19b44315a9b.872d58036113eeb1.jpg)\n\n\n황하의 지류인 낙수(洛水)가 남쪽에 흐르고 있기 때문에 원래는 '낙(洛)'이라고만 불렸다. 수로를 이용한 교통이 편리하고, 사방이 평야였기 때문에 농업생산력도 뛰어났는데, 이렇게 좋은 입지조건들로 인해 고대부터 유명했다. 중원의 중심으로 예로부터 구주지복지(九州之腹地, 중화 9주 중에서도 배에 해당하는 지역)이라고 불렸다. 이후 주나라(서주) 때 수도인 호경(鎬京)의 별칭인 '종주(宗周)'에 버금가는 도시가 되어 '성주(成周)'로 불리다가 동주 때 수도가 되면서 낙읍(洛邑)으로 개명되었다.\nhttps://m.blog.naver.com/sjkim2090/30187289876\n\n삼국시대의 낙양 위치는 지금 낙양이랑 위치가 다르다.\n지금 현재의 낙양 위치는 수나라 이후부터 였던 것이다. (통일 왕조만 따졌을 때) 지금의 낙양 위치에는 과거에는 하남현이 위치해 있었다.\n!https://mblogthumb-phinf.pstatic.net/20140320_199/sjkim2090_1395243490150aJQUp_PNG/6.png?type=w2\nhttps://mapsengine.google.com/map/edit?mid=zKq_HSakzRno.kKvSHoznv5i0\n\n당시의 낙양성은 현 뤄양 시가지의 동쪽에 있었다. \n크게 동주, 후한-위, 수-당의 낙양성이 각각 구분된다. 지금의 낙양은 마지막 수당시대의 낙양성. 후한 당시의 낙양성도 지금의 뤄양의 일부지만 지금의 중심지보다는 약간 동북쪽에 있었으며(위의 지도상으로는 뤄양 시와 옌스 시 사이), 지금의 뤄양 자리에는 하남현이 있었다고....\n후한 말기 동탁이 반동탁 연합군을 피해 뤄양을 불태우고 장안으로 수도를 옮기면서 뤄양은 초토화가 된다. 거기다 조조가 도성을 허도로 옮겼지만, 허도는 임시 수도였을 뿐 곧 뤄양 복구를 시작했다. 이후 조조는 자신의 말년을 뤄양에서 보내다가 사망하였고 조비가 즉위해 위나라가 세워지자 다시 뤄양을 도읍으로 잡았으며, 허도는 허창이란 이름으로만 우대받았을 뿐 수도의 기능은 상실되고 모두 뤄양으로 이주되었다. 조비와 조예가 낙양에 화려한 전각들을 세우면서 뤄양은 곧 수도의 위엄을 되찾았다. 이 때문에 아직까지도 이곳 주민들은 동씨를 매우 싫어하는 반면에, 조씨는 대우해 준다.\n수문제가 중국을 통일한 뒤부터 뤄양은 '동도(東都)'로 불리며 수도 장안 다음으로 큰 도시가 된다. 이 시기에 뤄양이 지금의 위치로 옮겨졌다. 수양제가 뤄양을 동쪽의 수도로 만들면서 현 위치에 화끈하게 토목 공사를 벌여 지은 것.\n\n낙양(洛陽) \n섬서성 남정현(陝西省 南鄭縣)(城關鎮 南鄭縣, 현재 한중시)에서  하남성 낙양시(河南省 洛陽市)로 지명 이동\n\n낙양(洛陽)이란 지명은 현 감숙성(甘肅省) 난주(蘭州)아래 황하가 흘러가는 거대한 물줄기의 아래쪽에 위치했던 것임을 정확히 짚어낼 수 있게 되었다.\nhttps://m.cafe.daum.net/warong84/Hzgh/50\n\n현 낙양에 대한 의문\n우리역사 history\n(https://youtu.be/8C9WQCOU5FQ?si=urFcpZHe4iaz6EBZ)\n\n덕흥리 무덤 벽에 묵서는 다음과 같이 적혀 있다. “ 이 13개 군은 유주에 속하며, 部縣이 75개다. 유주의 관할 구역은 계(薊) 지역 전부이다. 지금의 관할구역은 연나라이다. 연나라는 낙양에서 2천3백리 떨어져 있다.  도위(都尉)는 1부이고 모두 13군이다.\n\n此 十三郡 屬 幽州 部縣 七十五 州治 廣薊 今治 燕國 去 洛陽二千三百里 都尉 一部 幷 十三郡.\n\n북경에서 낙양까지 1540리 정도 됩니다. 북경에서 한중까지 2300리 정도\n현재 낙양은 과거 낙양성이 아닙니다. 백제 위례성일 가능성이 있습니다.\n\n[삼국사기 권 제34잡지 제3  지리(地理)一 신라(新羅)  『신당서』·『구당서』의 전문에 대한 고찰]\n살펴보건대 양한지(兩漢志)에 “낙랑군(樂浪郡)은 낙양(洛陽)의 동북 방향 5,000리 거리에 있다.”라고 하였고, 주(注)에서는 “유주(幽州)에 속하며, 옛 조선국(朝鮮國)이다.”라고 하였다. 즉 계림(鷄林)과는 멀리 떨어져 있는 것 같다. 또한 서로 전하기를, “동해의 외딴 섬에 대인국(大人國) 이 있다.”라고 하였다. 하지만 이를 본 사람이 없으니 어찌 쇠뇌 군사를 두어 지키게 하는 것이 있겠는가?\n\nhttps://namu.wiki/w/%EC%A3%BC%EB%82%98%EB%9D%BC\n주나라 수도 = 낙읍\n\n사마광의 시 〈낙양 옛 성을 지나며 (過故洛陽城)〉 中\n“고금의 흥망성쇠를 알고 싶다면, 낙양성에 한번 가보라.”\n若問古今興廢事，請君只看洛陽城。\n\n\n東周 즉 낙양은 1165년 六經圖의  十五國風地理之圖에 당시 장안현이었던 서안이 낙양이라고 말한다.\n(https://m.cafe.daum.net/munmoo-chosunsa/3U53/2403?)\n\n\n통관고성(潼关古城)\n관문인데 거대 성벽과 도시",
  "color": "default",
  "labels": [
    "d681d9ed-1ad5-4666-a9d4-269e4225597d",
    "baf8ac0a-cbc0-4174-aafe-417a1cab2927"
  ],
  "pinned": false,
  "archived": true,
  "inTrash": false,
  "reminder": null,
  "createdAt": "2024-06-09T20:35:14.675000",
  "updatedAt": "2025-12-22T12:56:13.372000"
}