{
  "id": "f98bf586-b5bb-44b3-a731-074b295b5f49",
  "title": "MC-130",
  "content": "한·미 특수부대가 사용하는 MC-130 특수 수송기는 기존의 C-130H 수송기에 열추적 미사일 회피 기능이 있는 적외선 지형 회피 레이더와 위성위치확인시스템(GPS) 등 특수전 장비를 탑재해 악천후에도 75m 이하 저고도로 침투 작전이 가능하다.\n야간작전을 위해 지형 추적 및 회피 레이더도 장착했다.\n수송능력은 완전무장병력 74명, 최대화물탑재량은 15.9톤입니다.\n\nKAI와 Elisra이 합동으로 기존 한국공군이 보유중이던 C-130H를 개조한 기재이다.\n원래 한국군은 유사시 북한에 특수부대원들을 투입시킬 MC-130의 구매를 미국에서 계속 요청하고 있었다.\n그러나, 미국이 이를 거절하자 결국 이스라엘의 Elisra와 접촉해 기존 보유중이던 C-130H를 MC-130에 준하게 개조하려 했다. 처음에는 미국은 이마저도 못하도록 압력을 넣었지만 주한미군이 북한지역내 침투용 기체가 필요하다는 설득을 한국 국방부와 같이 설득하며 결국 미국은 개조를 허락했고 이에따라 한국공군은 MC-130K 4대를 보유하게 되었다.",
  "color": "default",
  "labels": [
    "7614a8cc-7612-44a0-80ce-fcaffc04867d"
  ],
  "pinned": false,
  "archived": true,
  "inTrash": false,
  "reminder": null,
  "createdAt": "2022-05-15T11:16:40.761000",
  "updatedAt": "2022-05-15T11:16:40.761000"
}